codeCalculater/__init__.py
codeCalculater-0.1.dist-info/LICENSE.txt
codeCalculater-0.1.dist-info/METADATA
codeCalculater-0.1.dist-info/WHEEL
codeCalculater-0.1.dist-info/top_level.txt
codeCalculater-0.1.dist-info/RECORD
