Metadata-Version: 2.1
Name: codeCalculater
Version: 0.1
Summary: Basic Calculater
Author: rsalmoshbb
Author-email: rsalmoshbb@gmail.com
Classifier: Programming Language :: Python :: 3
Classifier: License :: OSI Approved :: MIT License
Classifier: Operating System :: OS Independent
License-File: LICENSE.txt
